LICENSE
README.md
pyproject.toml
setup.cfg
setup.py
grokspeechrec.egg-info/PKG-INFO
grokspeechrec.egg-info/SOURCES.txt
grokspeechrec.egg-info/dependency_links.txt
grokspeechrec.egg-info/requires.txt
grokspeechrec.egg-info/top_level.txt
src/__init__.py
src/speechrec/__init__.py
src/speechrec/app.py