Metadata-Version: 2.1
Name: grokspeechrec
Version: 0.0.2
Summary: TEST APP TMLC
Home-page: https://github.com/visalakshi2001/grokspeechrec/
Author: GROKLEARNING
Author-email: GROKLEARNING <visalakshi2001@gmail.com>
License: MIT
Project-URL: Homepage, https://github.com/visalakshi2001/grokspeechrec
Project-URL: Bug Tracker, https://github.com/visalakshi2001/grokspeechrec/issues
Keywords: speech recognizer
Classifier: Programming Language :: Python :: 3
Classifier: License :: OSI Approved :: MIT License
Classifier: Operating System :: OS Independent
Requires-Python: >=3.7
License-File: LICENSE
